{
  "meta": {
    "iterations": 2000000,
    "updated_at": "2026-06-13T18:33:47.426532Z"
  },
  "markets": {
    "Alberto Niccolai": {
      "attempts_on_record": 30,
      "miss_rate": 0.03125,
      "prob_over20": 0.876036718898433,
      "prob_over25": 0.5793316200513985,
      "prob_over30": 0.3286756397308081,
      "prob_vittoria": 0.1226953191404258,
      "prob_podio": 0.4766302010939672,
      "positional_prob": {
        "1": 0.12268059791031345,
        "2": 0.19632005199220118,
        "3": 0.1576023596460531,
        "4": 0.11315852622106684,
        "5": 0.09538719192121181,
        "6": 0.08936609508573715,
        "7": 0.07822726591011349,
        "8": 0.059143628455731644,
        "9": 0.03803529470579413,
        "10": 0.02138079288106784
      },
      "odds_over20": 1.01,
      "odds_over25": 1.21,
      "odds_over30": 2.13,
      "odds_vittoria": 5.71,
      "odds_podio": 1.47,
      "positional_odds": {
        "1": 5.71,
        "2": 3.57,
        "3": 4.44,
        "4": 6.19,
        "5": 7.34,
        "6": 7.83,
        "7": 8.95,
        "8": 11.84,
        "9": 18.4,
        "10": 32.74
      },
      "expected_best": 25.300744,
      "expected_avg": 19.58997366666626,
      "prob_vittoria_ci": [
        0.12224061354960791,
        0.12315002473124367
      ]
    },
    "Andrea Della Maggiora": {
      "attempts_on_record": 30,
      "miss_rate": 0.03125,
      "prob_over20": 0.7230413087607371,
      "prob_over25": 0.6728238152855415,
      "prob_over30": 0.45943971680849577,
      "prob_vittoria": 0.3149605511834645,
      "prob_podio": 0.6058913232603022,
      "positional_prob": {
        "1": 0.31492276158576216,
        "2": 0.1936414537819327,
        "3": 0.09728440733889916,
        "4": 0.046896965455181724,
        "5": 0.02616957456381543,
        "6": 0.02461880717892316,
        "7": 0.032417137429385595,
        "8": 0.04127080937859321,
        "9": 0.0454976753486977,
        "10": 0.042878568214767786
      },
      "odds_over20": 1.01,
      "odds_over25": 1.04,
      "odds_over30": 1.52,
      "odds_vittoria": 2.22,
      "odds_podio": 1.16,
      "positional_odds": {
        "1": 2.22,
        "2": 3.61,
        "3": 7.2,
        "4": 14.93,
        "5": 26.75,
        "6": 28.43,
        "7": 21.59,
        "8": 16.96,
        "9": 15.39,
        "10": 16.33
      },
      "expected_best": 25.8813605,
      "expected_avg": 17.248413666663847,
      "prob_vittoria_ci": [
        0.314316786800406,
        0.315604315566523
      ]
    },
    "Andrea Picchi": {
      "attempts_on_record": 30,
      "miss_rate": 0.03125,
      "prob_over20": 0.20630931072067837,
      "prob_over25": 0.10725228243152705,
      "prob_over30": 0.09590012299631011,
      "prob_vittoria": 0.04396668099957001,
      "prob_podio": 0.10917972460826175,
      "positional_prob": {
        "1": 0.04396140578913163,
        "2": 0.04214067889816527,
        "3": 0.023094535819627057,
        "4": 0.021285307203919412,
        "5": 0.024715792631105335,
        "6": 0.02297455381692746,
        "7": 0.018369744538319247,
        "8": 0.01633754936759486,
        "9": 0.021898215267709843,
        "10": 0.03731190321451782
      },
      "odds_over20": 3.39,
      "odds_over25": 6.53,
      "odds_over30": 7.3,
      "odds_vittoria": 15.92,
      "odds_podio": 6.41,
      "positional_odds": {
        "1": 15.92,
        "2": 16.61,
        "3": 30.31,
        "4": 32.89,
        "5": 28.32,
        "6": 30.47,
        "7": 38.11,
        "8": 42.85,
        "9": 31.97,
        "10": 18.76
      },
      "expected_best": 14.0248615,
      "expected_avg": 8.011877249999731,
      "prob_vittoria_ci": [
        0.04368253638523506,
        0.04425082561390496
      ]
    },
    "Andrea Romboli": {
      "attempts_on_record": 8,
      "miss_rate": 0.18181818181818182,
      "prob_over20": 0.6195719128426147,
      "prob_over25": 0.4359739207823765,
      "prob_over30": 0.03384798456046319,
      "prob_vittoria": 0.02564073077807666,
      "prob_podio": 0.18766387008389748,
      "positional_prob": {
        "1": 0.025637654351847224,
        "2": 0.054713792931060344,
        "3": 0.1073199020146978,
        "4": 0.14065690146478027,
        "5": 0.12739589061640755,
        "6": 0.08848872669099633,
        "7": 0.05361945708143779,
        "8": 0.03500874868769684,
        "9": 0.030403939409088636,
        "10": 0.034466330050492426
      },
      "odds_over20": 1.13,
      "odds_over25": 1.61,
      "odds_over30": 20.68,
      "odds_vittoria": 27.3,
      "odds_podio": 3.73,
      "positional_odds": {
        "1": 27.3,
        "2": 12.79,
        "3": 6.52,
        "4": 4.98,
        "5": 5.49,
        "6": 7.91,
        "7": 13.05,
        "8": 20.0,
        "9": 23.02,
        "10": 20.31
      },
      "expected_best": 19.9297965,
      "expected_avg": 13.595396499999817,
      "prob_vittoria_ci": [
        0.025421669390933262,
        0.025859792165220056
      ]
    },
    "Antonio Nicolosi": {
      "attempts_on_record": 30,
      "miss_rate": 0.03125,
      "prob_over20": 0.35301040968770936,
      "prob_over25": 0.18922582322530324,
      "prob_over30": 0.007863764087077387,
      "prob_vittoria": 0.015774026779196624,
      "prob_podio": 0.12729868103956882,
      "positional_prob": {
        "1": 0.01577213417987302,
        "2": 0.04448532720091986,
        "3": 0.06705594160875869,
        "4": 0.07145628155776633,
        "5": 0.06592311153327,
        "6": 0.06125281207818827,
        "7": 0.06188721691746238,
        "8": 0.06468929660550918,
        "9": 0.06739689046643003,
        "10": 0.07062240663900415
      },
      "odds_over20": 1.98,
      "odds_over25": 3.7,
      "odds_over30": 89.02,
      "odds_vittoria": 44.38,
      "odds_podio": 5.5,
      "positional_odds": {
        "1": 44.38,
        "2": 15.74,
        "3": 10.44,
        "4": 9.8,
        "5": 10.62,
        "6": 11.43,
        "7": 11.31,
        "8": 10.82,
        "9": 10.39,
        "10": 9.91
      },
      "expected_best": 18.062776,
      "expected_avg": 11.436183500000114,
      "prob_vittoria_ci": [
        0.015601339728919108,
        0.01594671382947414
      ]
    },
    "Chiara Tomaiuolo": {
      "attempts_on_record": 24,
      "miss_rate": 0.038461538461538464,
      "prob_over20": 0.05292591222263332,
      "prob_over25": 0.026732198034058977,
      "prob_over30": 0.010587682369528914,
      "prob_vittoria": 0.005589332320030399,
      "prob_podio": 0.017915962521124366,
      "positional_prob": {
        "1": 0.005588661700744888,
        "2": 0.005897615357696346,
        "3": 0.0064575313702944555,
        "4": 0.007070439434084888,
        "5": 0.010075988601709744,
        "6": 0.019859521071839224,
        "7": 0.04259261110833375,
        "8": 0.07762235664650302,
        "9": 0.11361195820626906,
        "10": 0.13209718542218668
      },
      "odds_over20": 13.23,
      "odds_over25": 26.19,
      "odds_over30": 66.11,
      "odds_vittoria": 100.0,
      "odds_podio": 39.07,
      "positional_odds": {
        "1": 100.0,
        "2": 100.0,
        "3": 100.0,
        "4": 99.0,
        "5": 69.47,
        "6": 35.25,
        "7": 16.43,
        "8": 9.02,
        "9": 6.16,
        "10": 5.3
      },
      "expected_best": 14.459402,
      "expected_avg": 9.75280999999978,
      "prob_vittoria_ci": [
        0.005486007673855825,
        0.005692656966204973
      ]
    },
    "Daniele Ninci": {
      "attempts_on_record": 30,
      "miss_rate": 0.03125,
      "prob_over20": 0.7942591722248332,
      "prob_over25": 0.26656450306490803,
      "prob_over30": 0.007832765017049489,
      "prob_vittoria": 0.02222983310500685,
      "prob_podio": 0.18791986240412786,
      "positional_prob": {
        "1": 0.022227165925111234,
        "2": 0.06358146278058291,
        "3": 0.10211868219767035,
        "4": 0.1276178573214018,
        "5": 0.14343498475228716,
        "6": 0.1405774133879918,
        "7": 0.11845373194020897,
        "8": 0.08857121431785232,
        "9": 0.06427085937109434,
        "10": 0.047035944608308754
      },
      "odds_over20": 1.01,
      "odds_over25": 2.63,
      "odds_over30": 89.37,
      "odds_vittoria": 31.49,
      "odds_podio": 3.72,
      "positional_odds": {
        "1": 31.49,
        "2": 11.01,
        "3": 6.85,
        "4": 5.49,
        "5": 4.88,
        "6": 4.98,
        "7": 5.91,
        "8": 7.9,
        "9": 10.89,
        "10": 14.88
      },
      "expected_best": 22.2398215,
      "expected_avg": 16.692507416667368,
      "prob_vittoria_ci": [
        0.02202550525478973,
        0.022434160955223974
      ]
    },
    "Emanuele Bertolucci": {
      "attempts_on_record": 8,
      "miss_rate": 0.35714285714285715,
      "prob_over20": 0.4063783086507405,
      "prob_over25": 0.06777096687099388,
      "prob_over30": 0.026788696339109828,
      "prob_vittoria": 0.01622951311460656,
      "prob_podio": 0.07040038798836035,
      "positional_prob": {
        "1": 0.016227565865120232,
        "2": 0.020695395690646403,
        "3": 0.03349897515372694,
        "4": 0.0511248312753087,
        "5": 0.06476678498225266,
        "6": 0.06953506973953907,
        "7": 0.06637404389341599,
        "8": 0.05792931060340949,
        "9": 0.04613857921311803,
        "10": 0.04049242613607959
      },
      "odds_over20": 1.72,
      "odds_over25": 10.33,
      "odds_over30": 26.13,
      "odds_vittoria": 43.13,
      "odds_podio": 9.94,
      "positional_odds": {
        "1": 43.14,
        "2": 33.82,
        "3": 20.9,
        "4": 13.69,
        "5": 10.81,
        "6": 10.07,
        "7": 10.55,
        "8": 12.08,
        "9": 15.17,
        "10": 17.29
      },
      "expected_best": 15.1304605,
      "expected_avg": 11.537504166666821,
      "prob_vittoria_ci": [
        0.01605439111242334,
        0.016404635116789783
      ]
    },
    "Francesco Pepe": {
      "attempts_on_record": 30,
      "miss_rate": 0.03125,
      "prob_over20": 0.6832340029799105,
      "prob_over25": 0.40565533034008977,
      "prob_over30": 0.17916262512124637,
      "prob_vittoria": 0.1373218803435897,
      "prob_podio": 0.32707518774436767,
      "positional_prob": {
        "1": 0.1373054041893716,
        "2": 0.08978953157026447,
        "3": 0.0999710043493476,
        "4": 0.09157526371044343,
        "5": 0.08378543218517222,
        "6": 0.08204869269609559,
        "7": 0.07880317952307155,
        "8": 0.07146278058291257,
        "9": 0.06214617807328901,
        "10": 0.05350547417887317
      },
      "odds_over20": 1.02,
      "odds_over25": 1.73,
      "odds_over30": 3.91,
      "odds_vittoria": 5.1,
      "odds_podio": 2.14,
      "positional_odds": {
        "1": 5.1,
        "2": 7.8,
        "3": 7.0,
        "4": 7.64,
        "5": 8.35,
        "6": 8.53,
        "7": 8.88,
        "8": 9.8,
        "9": 11.26,
        "10": 13.08
      },
      "expected_best": 23.7116125,
      "expected_avg": 16.57284075000197,
      "prob_vittoria_ci": [
        0.13684486171901786,
        0.13779889896816153
      ]
    },
    "Francesco Rogo": {
      "attempts_on_record": 6,
      "miss_rate": 0.125,
      "prob_over20": 0.2278676639700809,
      "prob_over25": 0.11895693129206124,
      "prob_over30": 0.04751607451776447,
      "prob_vittoria": 0.026545703628891134,
      "prob_podio": 0.08201753947381578,
      "positional_prob": {
        "1": 0.02654251862220667,
        "2": 0.027196920461930712,
        "3": 0.028298255261710745,
        "4": 0.029183122531620257,
        "5": 0.030009998500224965,
        "6": 0.03360545918112283,
        "7": 0.04085337199420087,
        "8": 0.05497275408688697,
        "9": 0.07819577063440485,
        "10": 0.10594360845873119
      },
      "odds_over20": 3.07,
      "odds_over25": 5.88,
      "odds_over30": 14.73,
      "odds_vittoria": 26.37,
      "odds_podio": 8.53,
      "positional_odds": {
        "1": 26.37,
        "2": 25.74,
        "3": 24.74,
        "4": 23.99,
        "5": 23.33,
        "6": 20.83,
        "7": 17.13,
        "8": 12.73,
        "9": 8.95,
        "10": 6.61
      },
      "expected_best": 15.955017,
      "expected_avg": 11.041513583329465,
      "prob_vittoria_ci": [
        0.02632291348328533,
        0.02676849377449694
      ]
    },
    "Gianluca Becuzzi": {
      "attempts_on_record": 21,
      "miss_rate": 0.043478260869565216,
      "prob_over20": 0.4635385938421847,
      "prob_over25": 0.25518534443966684,
      "prob_over30": 0.012523124306270813,
      "prob_vittoria": 0.0203508894733158,
      "prob_podio": 0.13374248772536823,
      "positional_prob": {
        "1": 0.020348447732840075,
        "2": 0.04796580512923061,
        "3": 0.06544218367244913,
        "4": 0.07012798080287957,
        "5": 0.07501974703794431,
        "6": 0.08239464080387941,
        "7": 0.08638054291856222,
        "8": 0.08382642603609458,
        "9": 0.0741948707693846,
        "10": 0.06287656851472279
      },
      "odds_over20": 1.51,
      "odds_over25": 2.74,
      "odds_over30": 55.9,
      "odds_vittoria": 34.4,
      "odds_podio": 5.23,
      "positional_odds": {
        "1": 34.4,
        "2": 14.59,
        "3": 10.7,
        "4": 9.98,
        "5": 9.33,
        "6": 8.5,
        "7": 8.1,
        "8": 8.35,
        "9": 9.43,
        "10": 11.13
      },
      "expected_best": 18.747423,
      "expected_avg": 12.643115500000876,
      "prob_vittoria_ci": [
        0.02015519973811014,
        0.02054657920852146
      ]
    },
    "Matteo Brini": {
      "attempts_on_record": 30,
      "miss_rate": 0.03125,
      "prob_over20": 0.6826215213543594,
      "prob_over25": 0.4675019749407518,
      "prob_over30": 0.2560493185204444,
      "prob_vittoria": 0.1739767806965791,
      "prob_podio": 0.39492065238042856,
      "positional_prob": {
        "1": 0.1739559066140079,
        "2": 0.12635154726790984,
        "3": 0.09459581062840573,
        "4": 0.07668549717542368,
        "5": 0.06919362095685647,
        "6": 0.07523621456781483,
        "7": 0.08234514822776584,
        "8": 0.08021996700494925,
        "9": 0.06711593261010848,
        "10": 0.050114482827575864
      },
      "odds_over20": 1.03,
      "odds_over25": 1.5,
      "odds_over30": 2.73,
      "odds_vittoria": 4.02,
      "odds_podio": 1.77,
      "positional_odds": {
        "1": 4.02,
        "2": 5.54,
        "3": 7.4,
        "4": 9.13,
        "5": 10.12,
        "6": 9.3,
        "7": 8.5,
        "8": 8.73,
        "9": 10.43,
        "10": 13.97
      },
      "expected_best": 24.1448915,
      "expected_avg": 17.100350916665906,
      "prob_vittoria_ci": [
        0.17345138943361363,
        0.17450217195954457
      ]
    },
    "Tommaso Banchini": {
      "attempts_on_record": 29,
      "miss_rate": 0.0625,
      "prob_over20": 0.35337939861804146,
      "prob_over25": 0.18988730338089857,
      "prob_over30": 0.008033758987230383,
      "prob_vittoria": 0.006018319450416487,
      "prob_podio": 0.05499985000449986,
      "positional_prob": {
        "1": 0.006017597360395941,
        "2": 0.0151262310653402,
        "3": 0.03387941808728691,
        "4": 0.05218367244913263,
        "5": 0.06113183022546618,
        "6": 0.06536569514572814,
        "7": 0.07504574313852921,
        "8": 0.08629755536669499,
        "9": 0.09377043443483478,
        "10": 0.09806229065640154
      },
      "odds_over20": 1.98,
      "odds_over25": 3.69,
      "odds_over30": 87.13,
      "odds_vittoria": 100.0,
      "odds_podio": 12.73,
      "positional_odds": {
        "1": 100.0,
        "2": 46.28,
        "3": 20.66,
        "4": 13.41,
        "5": 11.45,
        "6": 10.71,
        "7": 9.33,
        "8": 8.11,
        "9": 7.47,
        "10": 7.14
      },
      "expected_best": 17.16037,
      "expected_avg": 12.237022083332457,
      "prob_vittoria_ci": [
        0.005911126091015213,
        0.006125512809817762
      ]
    },
    "Andrea Strappato": {
      "attempts_on_record": 25,
      "miss_rate": 0.10344827586206896,
      "prob_over20": 0.30900072997810063,
      "prob_over25": 0.02372878813635591,
      "prob_over30": 0.009347719568412948,
      "prob_vittoria": 0.005589332320030399,
      "prob_podio": 0.03250302490925272,
      "positional_prob": {
        "1": 0.005588661700744888,
        "2": 0.008674698795180723,
        "3": 0.0182657601359796,
        "4": 0.03544568314752787,
        "5": 0.05539469079638054,
        "6": 0.07202219667049943,
        "7": 0.08479178123281508,
        "8": 0.09611708243763435,
        "9": 0.10706444033394992,
        "10": 0.11126381042843574
      },
      "odds_over20": 2.27,
      "odds_over25": 29.5,
      "odds_over30": 74.88,
      "odds_vittoria": 100.0,
      "odds_podio": 21.54,
      "positional_odds": {
        "1": 100.0,
        "2": 80.69,
        "3": 38.32,
        "4": 19.75,
        "5": 12.64,
        "6": 9.72,
        "7": 8.26,
        "8": 7.28,
        "9": 6.54,
        "10": 6.29
      },
      "expected_best": 16.7956245,
      "expected_avg": 11.971179833333114,
      "prob_vittoria_ci": [
        0.005486007673855825,
        0.005692656966204973
      ]
    },
    "Giovanni Cerretani": {
      "attempts_on_record": 3,
      "miss_rate": 0.2,
      "prob_over20": 0.3227998160055198,
      "prob_over25": 0.17199884003479896,
      "prob_over30": 0.06979490615281542,
      "prob_vittoria": 0.0390453286401408,
      "prob_podio": 0.11962341129766108,
      "positional_prob": {
        "1": 0.03904064390341449,
        "2": 0.03958056291556267,
        "3": 0.04101784732290156,
        "4": 0.04105384192371144,
        "5": 0.042214667799830026,
        "6": 0.045042743588461734,
        "7": 0.04912513123031545,
        "8": 0.05306104084387342,
        "9": 0.054609808528720695,
        "10": 0.0545478178273259
      },
      "odds_over20": 2.17,
      "odds_over25": 4.07,
      "odds_over30": 10.03,
      "odds_vittoria": 17.93,
      "odds_podio": 5.85,
      "positional_odds": {
        "1": 17.93,
        "2": 17.69,
        "3": 17.07,
        "4": 17.05,
        "5": 16.58,
        "6": 15.54,
        "7": 14.25,
        "8": 13.19,
        "9": 12.82,
        "10": 12.83
      },
      "expected_best": 14.997684,
      "expected_avg": 8.928509916665709,
      "prob_vittoria_ci": [
        0.03877687019780812,
        0.039313787082473475
      ]
    },
    "Paolo Masini": {
      "attempts_on_record": 2,
      "miss_rate": 0.625,
      "prob_over20": 0.19047228583142506,
      "prob_over25": 0.09877203683889484,
      "prob_over30": 0.03930382088537344,
      "prob_vittoria": 0.024275771726848194,
      "prob_podio": 0.07236782896513104,
      "positional_prob": {
        "1": 0.024272859071139328,
        "2": 0.02392891066340049,
        "3": 0.024187371894215867,
        "4": 0.024567814827775834,
        "5": 0.025470679398090286,
        "6": 0.027701344798280257,
        "7": 0.030803879418087286,
        "8": 0.03355946608008799,
        "9": 0.03573913912913063,
        "10": 0.03749037644353347
      },
      "odds_over20": 3.68,
      "odds_over25": 7.09,
      "odds_over30": 17.81,
      "odds_vittoria": 28.84,
      "odds_podio": 9.67,
      "positional_odds": {
        "1": 28.84,
        "2": 29.25,
        "3": 28.94,
        "4": 28.49,
        "5": 27.48,
        "6": 25.27,
        "7": 22.72,
        "8": 20.86,
        "9": 19.59,
        "10": 18.67
      },
      "expected_best": 10.612641,
      "expected_avg": 9.400907416666753,
      "prob_vittoria_ci": [
        0.024062471586801304,
        0.024489071866895085
      ]
    }
  },
  "top_rankings": [
    {
      "ranking": [
        "Andrea Della Maggiora",
        "Alberto Niccolai",
        "Francesco Pepe",
        "Antonio Nicolosi",
        "Andrea Romboli",
        "Gianluca Becuzzi",
        "Daniele Ninci",
        "Matteo Brini",
        "Tommaso Banchini",
        "Chiara Tomaiuolo"
      ],
      "ranking_prob": 2.5e-06,
      "positions": [
        {
          "pos": 1,
          "player": "Andrea Della Maggiora",
          "player_pos_prob": 0.31492276158576216
        },
        {
          "pos": 2,
          "player": "Alberto Niccolai",
          "player_pos_prob": 0.19632005199220118
        },
        {
          "pos": 3,
          "player": "Francesco Pepe",
          "player_pos_prob": 0.0999710043493476
        },
        {
          "pos": 4,
          "player": "Antonio Nicolosi",
          "player_pos_prob": 0.07145628155776633
        },
        {
          "pos": 5,
          "player": "Andrea Romboli",
          "player_pos_prob": 0.12739589061640755
        },
        {
          "pos": 6,
          "player": "Gianluca Becuzzi",
          "player_pos_prob": 0.08239464080387941
        },
        {
          "pos": 7,
          "player": "Daniele Ninci",
          "player_pos_prob": 0.11845373194020897
        },
        {
          "pos": 8,
          "player": "Matteo Brini",
          "player_pos_prob": 0.08021996700494925
        },
        {
          "pos": 9,
          "player": "Tommaso Banchini",
          "player_pos_prob": 0.09377043443483478
        },
        {
          "pos": 10,
          "player": "Chiara Tomaiuolo",
          "player_pos_prob": 0.13209718542218668
        }
      ]
    },
    {
      "ranking": [
        "Andrea Della Maggiora",
        "Alberto Niccolai",
        "Matteo Brini",
        "Francesco Pepe",
        "Andrea Romboli",
        "Tommaso Banchini",
        "Daniele Ninci",
        "Gianluca Becuzzi",
        "Chiara Tomaiuolo",
        "Andrea Strappato"
      ],
      "ranking_prob": 2.5e-06,
      "positions": [
        {
          "pos": 1,
          "player": "Andrea Della Maggiora",
          "player_pos_prob": 0.31492276158576216
        },
        {
          "pos": 2,
          "player": "Alberto Niccolai",
          "player_pos_prob": 0.19632005199220118
        },
        {
          "pos": 3,
          "player": "Matteo Brini",
          "player_pos_prob": 0.09459581062840573
        },
        {
          "pos": 4,
          "player": "Francesco Pepe",
          "player_pos_prob": 0.09157526371044343
        },
        {
          "pos": 5,
          "player": "Andrea Romboli",
          "player_pos_prob": 0.12739589061640755
        },
        {
          "pos": 6,
          "player": "Tommaso Banchini",
          "player_pos_prob": 0.06536569514572814
        },
        {
          "pos": 7,
          "player": "Daniele Ninci",
          "player_pos_prob": 0.11845373194020897
        },
        {
          "pos": 8,
          "player": "Gianluca Becuzzi",
          "player_pos_prob": 0.08382642603609458
        },
        {
          "pos": 9,
          "player": "Chiara Tomaiuolo",
          "player_pos_prob": 0.11361195820626906
        },
        {
          "pos": 10,
          "player": "Andrea Strappato",
          "player_pos_prob": 0.11126381042843574
        }
      ]
    },
    {
      "ranking": [
        "Andrea Della Maggiora",
        "Alberto Niccolai",
        "Andrea Romboli",
        "Daniele Ninci",
        "Francesco Pepe",
        "Antonio Nicolosi",
        "Gianluca Becuzzi",
        "Matteo Brini",
        "Andrea Strappato",
        "Chiara Tomaiuolo"
      ],
      "ranking_prob": 2e-06,
      "positions": [
        {
          "pos": 1,
          "player": "Andrea Della Maggiora",
          "player_pos_prob": 0.31492276158576216
        },
        {
          "pos": 2,
          "player": "Alberto Niccolai",
          "player_pos_prob": 0.19632005199220118
        },
        {
          "pos": 3,
          "player": "Andrea Romboli",
          "player_pos_prob": 0.1073199020146978
        },
        {
          "pos": 4,
          "player": "Daniele Ninci",
          "player_pos_prob": 0.1276178573214018
        },
        {
          "pos": 5,
          "player": "Francesco Pepe",
          "player_pos_prob": 0.08378543218517222
        },
        {
          "pos": 6,
          "player": "Antonio Nicolosi",
          "player_pos_prob": 0.06125281207818827
        },
        {
          "pos": 7,
          "player": "Gianluca Becuzzi",
          "player_pos_prob": 0.08638054291856222
        },
        {
          "pos": 8,
          "player": "Matteo Brini",
          "player_pos_prob": 0.08021996700494925
        },
        {
          "pos": 9,
          "player": "Andrea Strappato",
          "player_pos_prob": 0.10706444033394992
        },
        {
          "pos": 10,
          "player": "Chiara Tomaiuolo",
          "player_pos_prob": 0.13209718542218668
        }
      ]
    },
    {
      "ranking": [
        "Andrea Della Maggiora",
        "Alberto Niccolai",
        "Francesco Pepe",
        "Andrea Romboli",
        "Daniele Ninci",
        "Gianluca Becuzzi",
        "Matteo Brini",
        "Andrea Strappato",
        "Francesco Rogo",
        "Tommaso Banchini"
      ],
      "ranking_prob": 2e-06,
      "positions": [
        {
          "pos": 1,
          "player": "Andrea Della Maggiora",
          "player_pos_prob": 0.31492276158576216
        },
        {
          "pos": 2,
          "player": "Alberto Niccolai",
          "player_pos_prob": 0.19632005199220118
        },
        {
          "pos": 3,
          "player": "Francesco Pepe",
          "player_pos_prob": 0.0999710043493476
        },
        {
          "pos": 4,
          "player": "Andrea Romboli",
          "player_pos_prob": 0.14065690146478027
        },
        {
          "pos": 5,
          "player": "Daniele Ninci",
          "player_pos_prob": 0.14343498475228716
        },
        {
          "pos": 6,
          "player": "Gianluca Becuzzi",
          "player_pos_prob": 0.08239464080387941
        },
        {
          "pos": 7,
          "player": "Matteo Brini",
          "player_pos_prob": 0.08234514822776584
        },
        {
          "pos": 8,
          "player": "Andrea Strappato",
          "player_pos_prob": 0.09611708243763435
        },
        {
          "pos": 9,
          "player": "Francesco Rogo",
          "player_pos_prob": 0.07819577063440485
        },
        {
          "pos": 10,
          "player": "Tommaso Banchini",
          "player_pos_prob": 0.09806229065640154
        }
      ]
    },
    {
      "ranking": [
        "Matteo Brini",
        "Andrea Della Maggiora",
        "Francesco Pepe",
        "Alberto Niccolai",
        "Andrea Romboli",
        "Emanuele Bertolucci",
        "Daniele Ninci",
        "Antonio Nicolosi",
        "Chiara Tomaiuolo",
        "Andrea Strappato"
      ],
      "ranking_prob": 2e-06,
      "positions": [
        {
          "pos": 1,
          "player": "Matteo Brini",
          "player_pos_prob": 0.1739559066140079
        },
        {
          "pos": 2,
          "player": "Andrea Della Maggiora",
          "player_pos_prob": 0.1936414537819327
        },
        {
          "pos": 3,
          "player": "Francesco Pepe",
          "player_pos_prob": 0.0999710043493476
        },
        {
          "pos": 4,
          "player": "Alberto Niccolai",
          "player_pos_prob": 0.11315852622106684
        },
        {
          "pos": 5,
          "player": "Andrea Romboli",
          "player_pos_prob": 0.12739589061640755
        },
        {
          "pos": 6,
          "player": "Emanuele Bertolucci",
          "player_pos_prob": 0.06953506973953907
        },
        {
          "pos": 7,
          "player": "Daniele Ninci",
          "player_pos_prob": 0.11845373194020897
        },
        {
          "pos": 8,
          "player": "Antonio Nicolosi",
          "player_pos_prob": 0.06468929660550918
        },
        {
          "pos": 9,
          "player": "Chiara Tomaiuolo",
          "player_pos_prob": 0.11361195820626906
        },
        {
          "pos": 10,
          "player": "Andrea Strappato",
          "player_pos_prob": 0.11126381042843574
        }
      ]
    }
  ],
  "signals": {
    "Alberto Niccolai": {
      "signal": "stabile",
      "confidence": 72
    },
    "Andrea Della Maggiora": {
      "signal": "caldo",
      "confidence": 72
    },
    "Andrea Picchi": {
      "signal": "stabile",
      "confidence": 72
    },
    "Andrea Romboli": {
      "signal": "stabile",
      "confidence": 39
    },
    "Antonio Nicolosi": {
      "signal": "stabile",
      "confidence": 72
    },
    "Chiara Tomaiuolo": {
      "signal": "stabile",
      "confidence": 67
    },
    "Daniele Ninci": {
      "signal": "stabile",
      "confidence": 72
    },
    "Emanuele Bertolucci": {
      "signal": "stabile",
      "confidence": 31
    },
    "Francesco Pepe": {
      "signal": "caldo",
      "confidence": 72
    },
    "Francesco Rogo": {
      "signal": "stabile",
      "confidence": 37
    },
    "Gianluca Becuzzi": {
      "signal": "stabile",
      "confidence": 64
    },
    "Matteo Brini": {
      "signal": "caldo",
      "confidence": 72
    },
    "Tommaso Banchini": {
      "signal": "stabile",
      "confidence": 69
    },
    "Andrea Strappato": {
      "signal": "stabile",
      "confidence": 63
    },
    "Giovanni Cerretani": {
      "signal": "stabile",
      "confidence": 24
    },
    "Paolo Masini": {
      "signal": "stabile",
      "confidence": 9
    }
  },
  "market_indicators": {
    "Alberto Niccolai": {
      "expected_score": 25.3,
      "temperature": "stabile"
    },
    "Andrea Della Maggiora": {
      "expected_score": 25.88,
      "temperature": "caldo"
    },
    "Andrea Picchi": {
      "expected_score": 14.02,
      "temperature": "stabile"
    },
    "Andrea Romboli": {
      "expected_score": 19.93,
      "temperature": "stabile"
    },
    "Antonio Nicolosi": {
      "expected_score": 18.06,
      "temperature": "stabile"
    },
    "Chiara Tomaiuolo": {
      "expected_score": 14.46,
      "temperature": "stabile"
    },
    "Daniele Ninci": {
      "expected_score": 22.24,
      "temperature": "stabile"
    },
    "Emanuele Bertolucci": {
      "expected_score": 15.13,
      "temperature": "stabile"
    },
    "Francesco Pepe": {
      "expected_score": 23.71,
      "temperature": "caldo"
    },
    "Francesco Rogo": {
      "expected_score": 15.96,
      "temperature": "stabile"
    },
    "Gianluca Becuzzi": {
      "expected_score": 18.75,
      "temperature": "stabile"
    },
    "Matteo Brini": {
      "expected_score": 24.14,
      "temperature": "caldo"
    },
    "Tommaso Banchini": {
      "expected_score": 17.16,
      "temperature": "stabile"
    },
    "Andrea Strappato": {
      "expected_score": 16.8,
      "temperature": "stabile"
    },
    "Giovanni Cerretani": {
      "expected_score": 15.0,
      "temperature": "stabile"
    },
    "Paolo Masini": {
      "expected_score": 10.61,
      "temperature": "stabile"
    }
  },
  "special_bets": {
    "outsider_on_podio": {
      "probability": 0.3587375,
      "odds": 1.95
    },
    "nuovo_cecchino": {
      "probability": 0.0057135,
      "odds": 100.0
    },
    "nessuno_sotto_10": {
      "probability": 0.0863545,
      "odds": 8.11
    },
    "record_personale_battuto": {
      "probability": 0.9492115,
      "odds": 1.01
    }
  }
}